{
  "__type__": "cc.SpriteFrame",
  "content": {
    "name": "TigerNormal23",
    "atlas": "5c42830e-d775-4941-9c03-8f114c9b18b7",
    "rect": {
      "x": 1170,
      "y": 1560,
      "width": 390,
      "height": 390
    },
    "offset": {
      "x": 0,
      "y": 0
    },
    "originalSize": {
      "width": 390,
      "height": 390
    },
    "rotated": false,
    "capInsets": [
      0,
      0,
      0,
      0
    ],
    "vertices": {
      "rawPosition": [],
      "indexes": [],
      "uv": [],
      "nuv": [],
      "minPos": {
        "x": 0,
        "y": 0,
        "z": 0
      },
      "maxPos": {
        "x": 0,
        "y": 0,
        "z": 0
      }
    },
    "texture": "3a2200fb-87fa-42c6-989e-b70ee5119d7e@6c48a",
    "packable": true,
    "pixelsToUnit": 100,
    "pivot": {
      "x": 0.5,
      "y": 0.5
    },
    "meshType": 0
  }
}